aiopulse2/__init__.py
aiopulse2/const.py
aiopulse2/devices.py
aiopulse2/errors.py
aiopulse2-1.0.0.dist-info/licenses/LICENSE
aiopulse2-1.0.0.dist-info/METADATA
aiopulse2-1.0.0.dist-info/WHEEL
aiopulse2-1.0.0.dist-info/top_level.txt
aiopulse2-1.0.0.dist-info/RECORD
