Metadata-Version: 2.4
Name: aiopulse2
Version: 1.0.0
Summary: Rollease Acmeda Automate Pulse Hub v2 integration.
Home-page: https://github.com/sillyfrog/aiopulse2
Download-URL: https://github.com/sillyfrog/aiopulse2/archive/v1.0.0.tar.gz
Author: Sillyfrog
Author-email: tgh@sillyfrog.com
License: apache-2.0
Keywords: automation
Classifier: Development Status :: 5 - Production/Stable
Classifier: Intended Audience :: Developers
Classifier: Operating System :: OS Independent
Classifier: Topic :: Software Development :: Libraries :: Python Modules
Classifier: License :: OSI Approved :: Apache Software License
Classifier: Programming Language :: Python :: 3
Requires-Python: >=3.11
License-File: LICENSE
Requires-Dist: async_timeout>=3.0
Requires-Dist: websockets>=10.1
Dynamic: author
Dynamic: author-email
Dynamic: classifier
Dynamic: description
Dynamic: description-content-type
Dynamic: download-url
Dynamic: home-page
Dynamic: keywords
Dynamic: license
Dynamic: license-file
Dynamic: requires-dist
Dynamic: requires-python
Dynamic: summary
